snake_charmer/__init__.py
snake_charmer/__main__.py
snake_charmer/api.py
snake_charmer/github_api.py
snake_charmer/hook_manager.py
snake_charmer/models.py
snake_charmer-0.13.1.dist-info/LICENSE
snake_charmer-0.13.1.dist-info/METADATA
snake_charmer-0.13.1.dist-info/WHEEL
snake_charmer-0.13.1.dist-info/top_level.txt
snake_charmer-0.13.1.dist-info/RECORD
