Metadata-Version: 2.1
Name: snake-charmer
Version: 0.13.1
Summary: A python package that enables a github repo to release a python project from a pull request
Home-page: https://github.com/stephend017/snake_charmer
Author: Stephen Davis
Author-email: stephenedavis17@gmail.com
License: MIT
Platform: UNKNOWN
Classifier: License :: OSI Approved :: MIT License
Classifier: Programming Language :: Python :: 3
Classifier: Programming Language :: Python :: 3.8
Requires-Dist: pygithub
Requires-Dist: sd-utils
